configutil/__init__.py
configutil/configutil.py
configutil-0.0.1.dev4.dist-info/DESCRIPTION.rst
configutil-0.0.1.dev4.dist-info/LICENSE.txt
configutil-0.0.1.dev4.dist-info/METADATA
configutil-0.0.1.dev4.dist-info/RECORD
configutil-0.0.1.dev4.dist-info/WHEEL
configutil-0.0.1.dev4.dist-info/metadata.json
configutil-0.0.1.dev4.dist-info/top_level.txt
