Metadata-Version: 2.0
Name: configutil
Version: 0.0.1.dev4
Summary: Arguments, configuration, and environment resolver
Home-page: https://github.com/silverfernsys/configutil
Author: Silver Fern Systems
Author-email: dev@silverfern.io
License: BSD
Keywords: config configuration arguments
Platform: UNKNOWN
Classifier: Development Status :: 1 - Planning
Classifier: Intended Audience :: Developers
Classifier: License :: OSI Approved :: BSD License
Classifier: Programming Language :: Python :: 2.7
Classifier: Programming Language :: Python :: 3.0
Classifier: Programming Language :: Python :: 3.1
Classifier: Programming Language :: Python :: 3.2
Classifier: Programming Language :: Python :: 3.3
Classifier: Programming Language :: Python :: 3.4
Classifier: Programming Language :: Python :: 3.5
Classifier: Programming Language :: Python :: 3.6
Provides-Extra: test
Requires-Dist: coverage; extra == 'test'
Requires-Dist: codecov; extra == 'test'
Requires-Dist: pytest; extra == 'test'
Requires-Dist: mock; extra == 'test'
